README.md
setup.py
pygreenfield/__init__.py
pygreenfield/api_client.py
pygreenfield/configuration.py
pygreenfield/rest.py
pygreenfield.egg-info/PKG-INFO
pygreenfield.egg-info/SOURCES.txt
pygreenfield.egg-info/dependency_links.txt
pygreenfield.egg-info/requires.txt
pygreenfield.egg-info/top_level.txt
pygreenfield/api/__init__.py
pygreenfield/api/api_keys_api.py
pygreenfield/api/apps_api.py
pygreenfield/api/authorization_api.py
pygreenfield/api/custodians_api.py
pygreenfield/api/health_api.py
pygreenfield/api/invoices_api.py
pygreenfield/api/lightning__internal_node_api.py
pygreenfield/api/lightning__store_api.py
pygreenfield/api/miscelleneous_api.py
pygreenfield/api/notifications__current_user_api.py
pygreenfield/api/payment_requests_api.py
pygreenfield/api/payout_processors_api.py
pygreenfield/api/pull_payments__management_api.py
pygreenfield/api/pull_payments__public_api.py
pygreenfield/api/pull_payments_payout__public_api.py
pygreenfield/api/server_info_api.py
pygreenfield/api/store_payment_methods__lightning_network_api.py
pygreenfield/api/store_payment_methods__lnurl_pay_api.py
pygreenfield/api/store_payment_methods__on_chain_api.py
pygreenfield/api/store_payment_methods_api.py
pygreenfield/api/store_wallet__on_chain_api.py
pygreenfield/api/stores__email_api.py
pygreenfield/api/stores__payout_processors_api.py
pygreenfield/api/stores__payouts_api.py
pygreenfield/api/stores__users_api.py
pygreenfield/api/stores_api.py
pygreenfield/api/users_api.py
pygreenfield/api/webhooks_api.py
pygreenfield/models/__init__.py
pygreenfield/models/add_customer_email_request.py
pygreenfield/models/all_of_application_user_data_created.py
pygreenfield/models/all_of_checkout_options_expiration_minutes.py
pygreenfield/models/all_of_checkout_options_monitoring_minutes.py
pygreenfield/models/all_of_create_lightning_invoice_request_expiry.py
pygreenfield/models/all_of_lightning_automated_transfer_settings_interval_seconds.py
pygreenfield/models/all_of_lightning_invoice_data_expires_at.py
pygreenfield/models/all_of_lightning_invoice_data_paid_at.py
pygreenfield/models/all_of_lightning_payment_data_created_at.py
