Metadata-Version: 2.1
Name: pygreenfield
Version: 1.0.0
Summary: BTCPay Greenfield API
Home-page: UNKNOWN
Author-email: 
License: UNKNOWN
Keywords: Swagger,BTCPay Greenfield API
Platform: UNKNOWN
